bertmoticon/__init__.py
bertmoticon-1.0.2.dist-info/METADATA
bertmoticon-1.0.2.dist-info/WHEEL
bertmoticon-1.0.2.dist-info/entry_points.txt
bertmoticon-1.0.2.dist-info/top_level.txt
bertmoticon-1.0.2.dist-info/RECORD
