Metadata-Version: 2.1
Name: bertmoticon
Version: 1.0.2
Summary: multilingual emoji prediction
Home-page: https://github.com/Stefanos-stk/Bertmoticon
Author: Stefanos Stoikos
Author-email: st.stoikos@gmail.com
License: MIT
Platform: UNKNOWN
Classifier: License :: OSI Approved :: MIT License
Classifier: Programming Language :: Python :: 3
Classifier: Programming Language :: Python :: 3.7
Requires-Dist: torch
Requires-Dist: transformers
Requires-Dist: requests
